ccpp/__init__.py
ccpp/__main__.py
ggpp/__init__.py
ggpp/__main__.py
ggpp/main.py
ggpp-1.1.2.dist-info/LICENSE
ggpp-1.1.2.dist-info/METADATA
ggpp-1.1.2.dist-info/WHEEL
ggpp-1.1.2.dist-info/entry_points.txt
ggpp-1.1.2.dist-info/top_level.txt
ggpp-1.1.2.dist-info/RECORD
