Metadata-Version: 2.1
Name: ggpp
Version: 1.1.2
Summary: An useful g++ interface, to run easily C/C++ code on Linux and Windows.
Home-page: https://github.com/davigsousa/ggpp
Author: Davi Sousa
Author-email: davi.gomes.sousa@ccc.ufcg.edu.br
License: MIT
Keywords: c++ cpp c h g++ interface
Platform: UNKNOWN
Classifier: Programming Language :: Python :: 3
Classifier: License :: OSI Approved :: MIT License
Classifier: Operating System :: OS Independent
Requires-Python: >=3.6
